{
  "id": "tracing/integrations/contribute",
  "title": "Contributing to MLflow Tracing",
  "description": "Welcome to the MLflow Tracing contribution guide! This step-by-step resource will assist you in implementing additional GenAI library integrations for tracing into MLflow.",
  "source": "@site/docs/tracing/integrations/contribute.mdx",
  "sourceDirName": "tracing/integrations",
  "slug": "/tracing/integrations/contribute",
  "permalink": "/tracing/integrations/contribute",
  "draft": false,
  "unlisted": false,
  "tags": [],
  "version": "current",
  "sidebarPosition": 100,
  "frontMatter": {
    "sidebar_position": 100,
    "sidebar_label": "Add New Integration"
  },
  "sidebar": "docsSidebar",
  "previous": {
    "title": "Instructor",
    "permalink": "/tracing/integrations/instructor"
  },
  "next": {
    "title": "APIs",
    "permalink": "/tracing/api/"
  }
}